lilgit_parser/__init__.py
lilgit_parser/_init_.py
lilgit_parser/lilgit_parser.py
lilgit_parser/parseHandler.py
lilgit_parser/parser.py
lilgit_parser-0.2.dist-info/LICENSE.md
lilgit_parser-0.2.dist-info/METADATA
lilgit_parser-0.2.dist-info/WHEEL
lilgit_parser-0.2.dist-info/top_level.txt
lilgit_parser-0.2.dist-info/RECORD
