Metadata-Version: 2.1
Name: lilgit-parser
Version: 0.2
Summary: Server-side extension for lilgit parser
Home-page: https://github.com/mkery/Verdant
Author: Mary Beth Kery
Author-email: mkery@cs.cmu.edu
License: UNKNOWN
Platform: UNKNOWN
Classifier: Programming Language :: Python :: 3
Classifier: License :: OSI Approved :: MIT License
Classifier: Operating System :: OS Independent
